{
    "naver": "https://m.comic.naver.com/webtoon/weekday.nhn",
    "daum": "http://webtoon.daum.net/data/pc/webtoon/list_serialized/",
    "kakao": "https://api2-page.kakao.com/api/v7/store/section_container/list?agent=web&category=10&subcategory=1000&day=",
    "kakao-thumb": "https://dn-img-page.kakao.com/download/resource?kid=",
    "lezhin": "https://www.lezhin.com/api/v2/inventory_groups/home_scheduled",
    "lezhin-thumb": "https://cdn.lezhin.com/v2",
    "toomics": "https://www.toomics.com/webtoon/weekly/dow/",
    "toptoon": "https://toptoon.com/weekly",
    "misterblue": "https://www.mrblue.com/webtoon/all"
}
